{
    "author": "Nicolas-kings",
    "scriptable": true,
    "Email": "nicolas-king@qq.com",
    "repo": "https://github.com/Nicolasking007/Scriptable",
    "icon": "https://pic.rmb.bdstatic.com/bjh/6a9bfc89880d4a776f6406dd10249483.jpeg",
    "ONE-Tool": {
        "version": "1.8.1",
        "author": "Nicolas-kings",
        "description": "一个整合欢迎语、农历时间、每日情话、当日天气、手机电量、今年百分比的小组件",
        "scriptURL": "https://raw.githubusercontent.com/Nicolasking007/Scriptable/main/ONE-Tool/ONE-Tool.Enc.js",
        "cdn_scriptURL": "https://cdn.jsdelivr.net/gh/Nicolasking007/CDN@latest/Scriptable/ONE-Tool.Enc.js",
        "CY_scriptURL": "https://cdn.jsdelivr.net/gh/Nicolasking007/CDN@latest/Scriptable/ONE-Tool_CY.Enc.js",
        "thumb": "https://i.loli.net/2021/03/27/sH1AGgCmOK3ilqu.jpg",
        "wxurl": "https://mp.weixin.qq.com/s/z3AqWzHsF_MQ1ucVHEImIg",
        "name": "ONE-Tool",
        "title": "ONE-Tool",
        "images": [
            "https://i.loli.net/2021/03/27/sH1AGgCmOK3ilqu.jpg"
        ],
        "notes": "\n- 新增彩云天气版，打印日志调整、其他细节优化 \n- 使用中若发现问题，请前往公众号曰坛反馈\n- 发布时间：2022-07-09 21:48",
        "Updated": "2021-10-26 18:00"
    },
    "ONE-Progress": {
        "version": "1.5",
        "author": "Nicolas-kings",
        "description": "一个查看今天、本周、本月、今年和今生进度的小组件",
        "scriptURL": "https://raw.githubusercontent.com/Nicolasking007/Scriptable/main/ONE-Progress/ONE-Progress.Enc.js",
        "cdn_scriptURL": "https://cdn.jsdelivr.net/gh/Nicolasking007/CDN@latest/Scriptable/ONE-Progress.Enc.js",
        "thumb": "https://i.loli.net/2021/03/27/pz7i8DsA3WkGaTU.jpg",
        "wxurl": "https://mp.weixin.qq.com/s/Uj_euR4e8-Wy25z9VUKbSw",
        "name": "ONE-Progress",
        "title": "人生进度条",
        "images": [
            "https://i.loli.net/2021/03/27/pz7i8DsA3WkGaTU.jpg"
        ],
        "notes": "\n- 修复背景报错，新增多个图片背景选项 \n- 使用中若发现问题，请前往公众号曰坛反馈\n- 发布时间：2021-10-26 18:00",
        "Updated": "2021-10-26 18:00"
    },
    "ONE-NBA": {
        "version": "1.9",
        "author": "Nicolas-kings",
        "description": "关注喜爱NBA球队赛事结果小组件",
        "scriptURL": "https://raw.githubusercontent.com/Nicolasking007/Scriptable/main/ONE-NBA/ONE-NBA.Enc.js",
        "cdn_scriptURL": "https://cdn.jsdelivr.net/gh/Nicolasking007/CDN@latest/Scriptable/ONE-NBA.Enc.js",
        "thumb": "https://i.loli.net/2021/03/27/yEZAWRdraFKMpJB.jpg",
        "wxurl": "https://mp.weixin.qq.com/s/xwa4P39JQzjFO6SCqBX_fQ",
        "name": "ONE-NBA",
        "title": "ONE-NBA",
        "images": [
            "https://i.loli.net/2021/03/27/yEZAWRdraFKMpJB.jpg"
        ],
        "notes": "\n- 修复bug，开启全新赛季 \n- 使用中若发现问题，请前往公众号曰坛反馈\n- 发布时间：2022-01-12 18:13",
        "Updated": "2022-01-12 18:13"
    },
    "ONE-Friday": {
        "version": "1.1",
        "author": "Nicolas-kings",
        "description": "今天是星期五吗小组件",
        "scriptURL": "https://raw.githubusercontent.com/Nicolasking007/Scriptable/main/ONE-Friday/ONE-Friday.Enc.js",
        "cdn_scriptURL": "https://cdn.jsdelivr.net/gh/Nicolasking007/CDN@latest/Scriptable/ONE-Friday.Enc.js",
        "thumb": "https://pic.rmb.bdstatic.com/bjh/56ffd9646ed482568653f1fc543c3dda.png",
        "wxurl": "https://mp.weixin.qq.com/s/UtyxlH3gf283ySaqBTXz5Q",
        "name": "ONE-Friday",
        "title": "今天是星期五吗",
        "images": [
            "https://shop.io.mi-img.com/app/shop/img?id=shop_9c96a5f405165fe3a4b3c59df3a1d363.png"
        ],
        "notes": "\n- 优化背景图片缓存处理 \n- 使用中若发现问题，请前往公众号曰坛反馈\n- 发布时间：2021-10-26 18:00",
        "Updated": "2021-10-26 18:00"
    },
    "ONE-cuntdown": {
        "version": "1.5.0",
        "author": "Nicolas-kings",
        "description": "简单的倒计时小组件",
        "scriptURL": "https://raw.githubusercontent.com/Nicolasking007/Scriptable/main/ONE-cuntdown/ONE-cuntdown.Enc.js",
        "cdn_scriptURL": "https://cdn.jsdelivr.net/gh/Nicolasking007/CDN@latest/Scriptable/ONE-cuntdown.Enc.js",
        "thumb": "https://i.loli.net/2021/03/27/64eOAa1FtvDBm7J.jpg",
        "wxurl": "https://mp.weixin.qq.com/s/z3AqWzHsF_MQ1ucVHEImIg",
        "name": "ONE-cuntdown",
        "title": "倒计时",
        "images": [
            "https://i.loli.net/2021/03/27/64eOAa1FtvDBm7J.jpg"
        ],
        "notes": "\n- 新增多个自定义配置项、优化脚本更新逻辑 \n- 使用中若发现问题，请前往公众号曰坛反馈\n- 发布时间：2022-05-15 18:00",
        "Updated": "2022-05-15 18:00"
    },
    "ONE-hotcomments": {
        "version": "2.9",
        "author": "Nicolas-kings",
        "description": "网易云热评小组件",
        "scriptURL": "https://raw.githubusercontent.com/Nicolasking007/Scriptable/main/ONE-hotcomments/ONE-hotcomments.Enc.js",
        "cdn_scriptURL": "https://cdn.jsdelivr.net/gh/Nicolasking007/CDN@latest/Scriptable/ONE-hotcomments.Enc.js",
        "thumb": "https://i.loli.net/2021/04/04/KQARiV18gzv2cDj.jpg",
        "wxurl": "https://mp.weixin.qq.com/s/26pBQdHqJ4mOmzphEtwK1Q",
        "name": "ONE-hotcomments",
        "title": "网易云热评",
        "images": [
            "https://i.loli.net/2021/04/04/KQARiV18gzv2cDj.jpg","https://i.loli.net/2021/03/27/WbFpYaeitnZ5Mzc.jpg"
        ],
        "notes": "\n- 适配上游接口,修复接口限流问题 \n- 使用中若发现问题，请前往公众号曰坛反馈\n- 更新时间：2022-03-27 17:00",
        "Updated": "2022-03-27 17:00"
    },
    "ONE-oilprice": {
        "version": "2.1",
        "author": "Nicolas-kings",
        "description": "支持全国所有省份的油价实时数据小组件",
        "scriptURL": "https://raw.githubusercontent.com/Nicolasking007/Scriptable/main/ONE-oilprice/ONE-oilprice.Enc.js",
        "cdn_scriptURL": "https://cdn.jsdelivr.net/gh/Nicolasking007/CDN@latest/Scriptable/ONE-oilprice.Enc.js",
        "thumb": "https://i.loli.net/2021/03/27/OLpBgxMtnSJHWmh.jpg",
        "wxurl": "https://mp.weixin.qq.com/s/DN9SWnESbedDVO5-cNQbfw",
        "name": "ONE-oilprice",
        "title": "每日油价",
        "images": [
            "https://i.loli.net/2021/03/27/OLpBgxMtnSJHWmh.jpg"
        ],
        "notes": "\n\n- 适配中石化接口字段调整,修复报错\n- 使用中若发现问题，请前往公众号曰坛反馈\n- 发布时间：2022-04-30 19:00",
        "Updated": "2022-04-30 19:00"
    },
    "ONE-Today": {
        "version": "1.8",
        "author": "Nicolas-kings",
        "description": "简单的日历小组件",
        "scriptURL": "https://raw.githubusercontent.com/Nicolasking007/Scriptable/main/ONE-Today/ONE-Today.Enc.js",
        "cdn_scriptURL": "https://cdn.jsdelivr.net/gh/Nicolasking007/CDN@latest/Scriptable/ONE-Today.Enc.js",
        "thumb": "https://i.loli.net/2021/03/27/TbFJz8slCiYONV4.jpg",
        "wxurl": "https://mp.weixin.qq.com/s/UtyxlH3gf283ySaqBTXz5Q",
        "name": "ONE-Today",
        "title": "ONE-Today",
        "images": [
            "https://i.loli.net/2021/03/27/TbFJz8slCiYONV4.jpg"
        ],
        "notes": "\n- 修复背景报错，新增多个图片背景选项 \n- 使用中若发现问题，请前往公众号曰坛反馈\n- 发布时间：2021-10-26 18:00",
        "Updated": "2021-10-26 18:00"
    },
    "捷径社区数据": {
        "version": "1.0",
        "author": "Nicolas-kings",
        "description": "捷径社区数据看板",
        "scriptURL": "https://raw.githubusercontent.com/Nicolasking007/Scriptable/main/捷径社区数据看板/捷径社区数据.Enc.js",
        "cdn_scriptURL": "https://cdn.jsdelivr.net/gh/Nicolasking007/CDN@latest/Scriptable/捷径社区数据.Enc.js",
        "thumb": "https://i.loli.net/2021/04/25/yJx4jGIMCRKodqg.jpg",
        "wxurl": "https://nkupp.com",
        "name": "捷径社区数据",
        "title": "捷径社区数据",
        "images": [
            "https://i.loli.net/2021/04/25/yJx4jGIMCRKodqg.jpg"
        ],
        "notes": "\n- 支持脚本更新模块\n- 增加数据缓存\n- 使用中若发现问题，请前往公众号曰坛反馈\n- 发布时间：2021-10-26 18:00",
        "Updated": "2021-10-26 18:00"
    },
    "捷径盒数据": {
        "version": "1.0",
        "author": "Nicolas-kings",
        "description": "捷径盒数据看板",
        "scriptURL": "https://raw.githubusercontent.com/Nicolasking007/Scriptable/main/捷径盒数据看板/捷径盒数据.Enc.js",
        "cdn_scriptURL": "https://cdn.jsdelivr.net/gh/Nicolasking007/CDN@latest/Scriptable/捷径盒数据.Enc.js",
        "thumb": "https://i.loli.net/2021/04/25/yJx4jGIMCRKodqg.jpg",
        "wxurl": "https://nkupp.com",
        "name": "捷径盒数据",
        "title": "捷径盒数据",
        "images": [
            "https://i.loli.net/2021/04/25/yJx4jGIMCRKodqg.jpg"
        ],
        "notes": "\n- 支持脚本更新模块\n- 增加数据缓存\n- 使用中若发现问题，请前往公众号曰坛反馈\n- 发布时间：2021-10-26 18:00",
        "Updated": "2021-10-26 18:00"
    },
    "ONE-COVID_Vac": {
        "version": "1.5",
        "author": "Nicolas-kings",
        "description": "中国/全球疫苗数据",
        "scriptURL": "https://raw.githubusercontent.com/Nicolasking007/Scriptable/main/COVID-19/ONE-COVID_Vac.Enc.js",
        "cdn_scriptURL": "https://cdn.jsdelivr.net/gh/Nicolasking007/CDN@latest/Scriptable/ONE-COVID_Vac.Enc.js",
        "thumb": "https://i.loli.net/2021/05/27/OTal5tm1IUvVBPi.jpg",
        "wxurl": "https://mp.weixin.qq.com/s/BglSVR8R7D6Rk-V-Tyh1Eg",
        "name": "ONE-COVID_Vac",
        "title": "ONE-COVID_Vac",
        "images": [
            "https://i.loli.net/2021/05/27/OTal5tm1IUvVBPi.jpg"
        ],
        "notice": "数据说明：疫苗接种数据来自于国家卫健委发布。\n接种剂次：数据口径为接种剂次，而非接种人数。目前上市疫苗均需接种两个剂次。\n生产厂商：国药/北京，国药/武汉，科兴生物，康希诺，牛津/阿斯利康...",
        "notes": "\n- 修复背景报错，新增多个图片背景选项\n- 使用中若发现问题，请前往公众号曰坛反馈\n- 发布时间：2021-10-26 18:00",
        "Updated": "2021-10-26 18:00"
    },
    "ONE-memorandum": {
        "version": "1.0",
        "author": "Nicolas-kings",
        "description": "日历壁纸",
        "scriptURL": "https://raw.githubusercontent.com/Nicolasking007/Scriptable/main/ONE-memorandum/ONE-memorandum.Enc.js",
        "cdn_scriptURL": "https://cdn.jsdelivr.net/gh/Nicolasking007/CDN@latest/Scriptable/ONE-memorandum.Enc.js",
        "thumb": "https://i.loli.net/2021/05/31/anHWT9g6Bzmxoi7.jpg",
        "wxurl": "https://nkupp.com",
        "name": "ONE-memorandum",
        "title": "ONE-memorandum",
        "images": [
            "https://i.loli.net/2021/05/31/anHWT9g6Bzmxoi7.jpg"
        ],
        "notice": "",
        "notes": "\n- 首次发布\n- 使用中若发现问题，请前往公众号曰坛反馈\n- 发布时间：2021-10-26 18:00",
        "Updated": "2021-10-26 18:00"
    },
    "ONE-NBAMATCH": {
        "version": "1.4",
        "author": "Nicolas-kings",
        "description": "关注喜爱NBA球队赛事结果小组件",
        "scriptURL": "https://raw.githubusercontent.com/Nicolasking007/Scriptable/main/ONE-NBAMATCH/ONE-NBAMATCH.Enc.js",
        "cdn_scriptURL": "https://cdn.jsdelivr.net/gh/Nicolasking007/CDN@latest/Scriptable/ONE-NBAMATCH.Enc.js",
        "thumb": "https://i.loli.net/2021/06/04/ietfW3wKngVLBGX.jpg",
        "wxurl": "https://mp.weixin.qq.com/s/tLOD0cvNrIlXTVGFd-zcYQ",
        "name": "ONE-NBAMATCH",
        "title": "ONE-NBAMATCH",
        "images": [
            "https://i.loli.net/2021/06/04/ietfW3wKngVLBGX.jpg"
        ],
        "notice": "赛季结束或关注的球队争夺总冠军征程结束\n\n我们下赛季见 Good Luck！",
        "notes": "\n- 修复因混淆导致判断出错的问题 \n- 使用中若发现问题，请前往公众号曰坛反馈\n- 发布时间：2021-12-16 10:30",
        "Updated": "2021-12-16 10:30"
    },
    "ONE-LOLMATCH": {
        "version": "1.2",
        "author": "Nicolas-kings",
        "description": "关注喜爱lpl战队赛事结果小组件",
        "scriptURL": "https://raw.githubusercontent.com/Nicolasking007/Scriptable/main/ONE-LOLMATCH/ONE-LOLMATCH.Enc.js",
        "cdn_scriptURL": "https://cdn.jsdelivr.net/gh/Nicolasking007/CDN@latest/Scriptable/ONE-LOLMATCH.Enc.js",
        "thumb": "https://i.loli.net/2021/06/13/Uknrwv8LPTZEAmK.jpg",
        "wxurl": "https://mp.weixin.qq.com/s/WfPZTQonUpYpdQnmhe2Oxg",
        "name": "ONE-LOLMATCH",
        "title": "ONE-LOLMATCH",
        "images": [
            "https://i.loli.net/2021/06/13/Uknrwv8LPTZEAmK.jpg"
        ],
        "notice": "LPL赛季结束或关注的战队争夺S11总冠军征程结束\n\n我们下赛季见 Good Luck！",
        "notes": "\n- 修复背景报错，新增多个图片背景选项\n- 使用中若发现问题，请前往公众号曰坛反馈\n- 发布时间：2021-10-26 18:00",
        "Updated": "2021-12-16 10:30"
    },
    "ONE-FOOTMATCH": {
        "version": "1.0",
        "author": "Nicolas-kings",
        "description": "关注喜爱足球赛事结果小组件",
        "scriptURL": "https://raw.githubusercontent.com/Nicolasking007/Scriptable/main/ONE-FOOTMATCH/ONE-FOOTMATCH.Enc.js",
        "cdn_scriptURL": "https://cdn.jsdelivr.net/gh/Nicolasking007/CDN@latest/Scriptable/ONE-FOOTMATCH.Enc.js",
        "thumb": "https://i.loli.net/2021/06/13/6B3sTjg8VwaRGmP.jpg",
        "wxurl": "https://nkupp.com",
        "name": "ONE-FOOTMATCH",
        "title": "ONE-FOOTMATCH",
        "images": [
            "https://i.loli.net/2021/06/13/6B3sTjg8VwaRGmP.jpg"
        ],
        "notice": "赛季结束或关注的球队预选赛征程结束\n\n我们四年后再见 Good Luck！",
        "notes": "\n- 首次发布\n- 使用中若发现问题，请前往公众号曰坛反馈\n- 发布时间：2021-10-26 18:00",
        "Updated": "2021-12-16 10:30"
    },
    "ONE-Olympic": {
        "version": "1.3",
        "author": "Nicolas-kings",
        "description": "夏季奥林匹克运动会奖牌榜小组件",
        "scriptURL": "https://raw.githubusercontent.com/Nicolasking007/Scriptable/main/ONE-Olympic/ONE-Olympic.Enc.js",
        "cdn_scriptURL": "https://cdn.jsdelivr.net/gh/Nicolasking007/CDN@latest/Scriptable/ONE-Olympic.Enc.js",
        "thumb": "https://i.loli.net/2021/07/24/sfr1aeEKlyRnIu4.jpg",
        "wxurl": "https://mp.weixin.qq.com/s/mRRVjs8tGahSSUanid4q4g",
        "name": "ONE-Olympic",
        "title": "ONE-Olympic",
        "images": [
            "https://i.loli.net/2021/07/24/sfr1aeEKlyRnIu4.jpg"
        ],
        "notice": "本届奥运会暨第32届夏季奥林匹克运动会结束\n\n我们2024年巴黎奥运会见 Good Luck！",
        "notes": "\n- 修复背景报错，新增多个图片背景选项 \n- 使用中若发现问题，请前往公众号曰坛反馈\n- 发布时间：2021-10-26 18:00",
        "Updated": "2021-12-16 10:30"
    },
    "ONE-Download": {
        "version": "1.1.0",
        "author": "Nicolas-kings",
        "description": "脚本下载器",
        "scriptURL": "https://raw.githubusercontent.com/Nicolasking007/Scriptable/main/ONE-Download/ONE-Download.Enc.js",
        "cdn_scriptURL": "https://cdn.jsdelivr.net/gh/Nicolasking007/CDN@latest/Scriptable/ONE-Download.Enc.js",
        "thumb": "https://i.loli.net/2021/07/24/sfr1aeEKlyRnIu4.jpg",
        "wxurl": "https://nkupp.com",
        "path":"Menulist",
        "name": "ONE-Download",
        "title": "ONE-Download",
        "images": [
            "https://i.loli.net/2021/07/24/sfr1aeEKlyRnIu4.jpg"
        ],
        "notice": "",
        "notes": "\n- 增加第三方分享作品、网友投稿选项 \n- 使用中若发现问题，请前往公众号曰坛反馈\n- 发布时间：2022-07-10 16:48",
        "Updated": "2021-12-16 13:00"
    },
    "ONE-Quotations": {
        "version": "1.0.0",
        "author": "Nicolas-kings",
        "description": "毛主席语录小组件",
        "scriptURL": "https://raw.githubusercontent.com/Nicolasking007/Scriptable/main/ONE-Quotations/ONE-Quotations.Enc.js",
        "cdn_scriptURL": "https://cdn.jsdelivr.net/gh/Nicolasking007/CDN@latest/Scriptable/ONE-Quotations.Enc.js",
        "thumb": "https://i.loli.net/2021/07/24/sfr1aeEKlyRnIu4.jpg",
        "wxurl": "https://nkupp.com",
        "path":"Quotations",
        "name": "ONE-Quotations",
        "title": "ONE-Quotations",
        "images": [
            "https://i.loli.net/2021/07/24/sfr1aeEKlyRnIu4.jpg"
        ],
        "notes": "\n- 修复背景报错，新增多个图片背景选项 \n- 使用中若发现问题，请前往公众号曰坛反馈\n- 发布时间：2021-05-27 13:00",
        "Updated": "2021-05-27 13:00"
    },
    "ONE-Forwardtime": {
        "version": "1.0.0",
        "author": "Nicolas-kings",
        "description": "正向计时小组件",
        "scriptURL": "https://raw.githubusercontent.com/Nicolasking007/Scriptable/main/ONE-Forwardtime/ONE-Forwardtime.Enc.js",
        "cdn_scriptURL": "https://cdn.jsdelivr.net/gh/Nicolasking007/CDN@latest/Scriptable/ONE-Forwardtime.Enc.js",
        "thumb": "https://i.loli.net/2021/07/24/sfr1aeEKlyRnIu4.jpg",
        "wxurl": "https://mp.weixin.qq.com/s/Lt62ojubzBlK_9ktbTxC8Q",
        "path":"https://nkupp.com",
        "name": "ONE-Forwardtime",
        "title": "ONE-Forwardtime",
        "images": [
            "https://i.loli.net/2021/07/24/sfr1aeEKlyRnIu4.jpg"
        ],
        "notes": "\n- 首次发布 \n- 使用中若发现问题，请前往公众号曰坛反馈\n- 发布时间：2022-05-15 18:00",
        "Updated": "2022-05-15 18:00"
    },
    "ONE-COVID19_Datasheet": {
        "version": "1.0.0",
        "author": "Nicolas-kings",
        "description": "COVID-19疫情数据列表小组件",
        "scriptURL": "https://raw.githubusercontent.com/Nicolasking007/Scriptable/main/ONE-COVID19_Datasheet/ONE-COVID19_Datasheet.Enc.js",
        "cdn_scriptURL": "https://cdn.jsdelivr.net/gh/Nicolasking007/CDN@latest/Scriptable/ONE-COVID19_Datasheet.Enc.js",
        "thumb": "https://i.loli.net/2021/07/24/sfr1aeEKlyRnIu4.jpg",
        "wxurl": "https://mp.weixin.qq.com/s/Lt62ojubzBlK_9ktbTxC8Q",
        "path":"https://nkupp.com",
        "name": "ONE-COVID19_Datasheet",
        "title": "ONE-COVID19_Datasheet",
        "images": [
            "https://i.loli.net/2021/07/24/sfr1aeEKlyRnIu4.jpg"
        ],
        "notes": "\n- 首次发布 \n- 使用中若发现问题，请前往公众号曰坛反馈\n- 发布时间：2022-06-19 18:00",
        "Updated": "2022-06-19 18:00"
    },
    "copyright": "© 2022 Copyright Nicolas-kings - 不允许基于该数据私自改编，修改任何作品等，进行上述操作前请先与我取得联系，谢谢！"
}